setup.py
Shotgun.egg-info/PKG-INFO
Shotgun.egg-info/SOURCES.txt
Shotgun.egg-info/dependency_links.txt
Shotgun.egg-info/not-zip-safe
Shotgun.egg-info/requires.txt
Shotgun.egg-info/top_level.txt
shotgun/__init__.py
shotgun/config.py
shotgun/driver.py
shotgun/logger.py
shotgun/manager.py
shotgun/settings.py
shotgun/utils.py
shotgun/test/__init__.py
shotgun/test/test_config.py
shotgun/test/test_driver.py