Metadata-Version: 1.1
Name: Shotgun
Version: 0.1.0
Summary: Shotgun package
Home-page: https://github.com/kozhukalov/shotgun.git
Author: UNKNOWN
Author-email: UNKNOWN
License: UNKNOWN
Keywords: shotgun
Platform: UNKNOWN
Classifier: Development Status :: 4 - Beta
Classifier: Programming Language :: Python
